PruebasLoewe/__init__.py
PruebasLoewe/despedidas/__init__.py
PruebasLoewe/despedidas/despedir.py
PruebasLoewe/saludos/__init__.py
PruebasLoewe/saludos/saludar.py
test/__init__.py
test/test.py
PruebasLoewe-4.3.dist-info/LICENSE
PruebasLoewe-4.3.dist-info/METADATA
PruebasLoewe-4.3.dist-info/WHEEL
PruebasLoewe-4.3.dist-info/top_level.txt
PruebasLoewe-4.3.dist-info/RECORD
