Metadata-Version: 2.1
Name: PruebasLoewe
Version: 4.3
Summary: Una biblioteca de ejemplo
Home-page: https://github.com/tu_usuario/my_library
Author: Carlos Moreno
Author-email: carlos_moreno@loewe.com
License: MIT
Classifier: Development Status :: 3 - Alpha
Classifier: Intended Audience :: Developers
Classifier: License :: OSI Approved :: MIT License
Classifier: Programming Language :: Python :: 3
Classifier: Programming Language :: Python :: 3.7
License-File: LICENSE
Requires-Dist: numpy >=1.11.1
Requires-Dist: pandas >=0.23.0
